tiwarilog/__init__.py
tiwarilog-0.0.2.dist-info/LICENSE.txt
tiwarilog-0.0.2.dist-info/METADATA
tiwarilog-0.0.2.dist-info/WHEEL
tiwarilog-0.0.2.dist-info/top_level.txt
tiwarilog-0.0.2.dist-info/RECORD
