Metadata-Version: 2.1
Name: tiwarilog
Version: 0.0.2
Summary: module to log requests and response
Home-page: UNKNOWN
Author: Priyansh
Author-email: 17bcs140@ietdavv.edu.in
License: UNKNOWN
Platform: UNKNOWN
Classifier: Programming Language :: Python :: 3
Classifier: License :: OSI Approved :: MIT License
Classifier: Operating System :: OS Independent
Requires-Python: >=3.6
